mdformat_tight_lists/__init__.py
mdformat_tight_lists/plugin.py
mdformat_tight_lists-0.1.1.dist-info/entry_points.txt
mdformat_tight_lists-0.1.1.dist-info/licenses/LICENSE
mdformat_tight_lists-0.1.1.dist-info/WHEEL
mdformat_tight_lists-0.1.1.dist-info/METADATA
mdformat_tight_lists-0.1.1.dist-info/RECORD
