Metadata-Version: 2.4
Name: mdformat_tight_lists
Version: 0.1.1
Summary: An mdformat plugin for creating tight lists (no empty lines between list items).
Keywords: mdformat,markdown,markdown-it,formatter,lists
Author-email: Joseph Monaco <joe@selfmotion.net>
Requires-Python: >=3.10
Classifier: Development Status :: 4 - Beta
Classifier: Intended Audience :: Developers
Classifier: License :: OSI Approved :: MIT License
Classifier: Programming Language :: Python :: 3
Classifier: Programming Language :: Python :: 3.10
Classifier: Programming Language :: Python :: 3.11
Classifier: Programming Language :: Python :: 3.12
Classifier: Programming Language :: Python :: 3.13
Classifier: Topic :: Software Development :: Libraries :: Python Modules
Classifier: Topic :: Text Processing :: Markup :: Markdown
License-File: LICENSE
Requires-Dist: mdformat>=0.7.0
Requires-Dist: mdformat-frontmatter>=2.0.0
Requires-Dist: pytest>=7.0 ; extra == "test"
Requires-Dist: pytest-cov>=4.0 ; extra == "test"
Project-URL: Homepage, https://github.com/jdmonaco/mdformat-tight-lists
Provides-Extra: test
